clld/__init__.py
clld/__main__.py
clld/_compat.py
clld/appconf.ini
clld/cliutil.py
clld/config.py
clld/interfaces.py
clld/util.py
clld/commands/__init__.py
clld/commands/create.py
clld/commands/create_downloads.py
clld/commands/initdb.py
clld/db/__init__.py
clld/db/fts.py
clld/db/meta.py
clld/db/util.py
clld/db/models/__init__.py
clld/db/models/_mixins.py
clld/db/models/common.py
clld/db/models/config.py
clld/db/models/contribution.py
clld/db/models/contributor.py
clld/db/models/dataset.py
clld/db/models/gloss.py
clld/db/models/language.py
clld/db/models/parameter.py
clld/db/models/sentence.py
clld/db/models/source.py
clld/db/models/unit.py
clld/db/models/unitparameter.py
clld/db/models/unitvalue.py
clld/db/models/value.py
clld/db/models/valueset.py
clld/lib/__init__.py
clld/lib/bibo.py
clld/lib/bibtex.py
clld/lib/coins.py
clld/lib/latex.py
clld/lib/rdf.py
clld/locale/clld.pot
clld/locale/en/LC_MESSAGES/clld.mo
clld/locale/en/LC_MESSAGES/clld.po
clld/project_template/cookiecutter.json
clld/project_template/{{cookiecutter.directory_name}}/.gitignore
clld/project_template/{{cookiecutter.directory_name}}/CONTRIBUTING.md
clld/project_template/{{cookiecutter.directory_name}}/MANIFEST.in
clld/project_template/{{cookiecutter.directory_name}}/development.ini
clld/project_template/{{cookiecutter.directory_name}}/pyproject.toml
clld/project_template/{{cookiecutter.directory_name}}/requirements.txt
clld/project_template/{{cookiecutter.directory_name}}/setup.cfg
clld/project_template/{{cookiecutter.directory_name}}/setup.py
clld/project_template/{{cookiecutter.directory_name}}/{{cookiecutter.directory_name}}/__init__.py
clld/project_template/{{cookiecutter.directory_name}}/{{cookiecutter.directory_name}}/adapters.py
clld/project_template/{{cookiecutter.directory_name}}/{{cookiecutter.directory_name}}/appconf.ini
clld/project_template/{{cookiecutter.directory_name}}/{{cookiecutter.directory_name}}/assets.py
clld-11.5.0.dist-info/METADATA
clld-11.5.0.dist-info/WHEEL
clld-11.5.0.dist-info/entry_points.txt
clld-11.5.0.dist-info/top_level.txt
clld-11.5.0.dist-info/RECORD
