Metadata-Version: 2.1
Name: clld
Version: 11.5.0
Summary: Python library supporting the development of cross-linguistic databases
Home-page: https://clld.org
Author: Robert Forkel
Author-email: robert_forkel@eva.mpg.de
License: Apache 2.0
Project-URL: Source, https://github.com/clld/clld
Project-URL: Bug Tracker, https://github.com/clld/clld/issues
Keywords: web pyramid LRL Linguistics
Classifier: Development Status :: 5 - Production/Stable
Classifier: Intended Audience :: Developers
Classifier: Intended Audience :: Science/Research
Classifier: Natural Language :: English
Classifier: Operating System :: OS Independent
Classifier: Programming Language :: Python :: 3
Classifier: Programming Language :: Python :: 3.8
Classifier: Programming Language :: Python :: 3.9
Classifier: Programming Language :: Python :: 3.10
Classifier: Programming Language :: Python :: 3.11
Classifier: Programming Language :: Python :: 3.12
Classifier: Programming Language :: Python :: 3.13
Classifier: Programming Language :: Python :: Implementation :: CPython
Classifier: Programming Language :: Python :: Implementation :: PyPy
Classifier: License :: OSI Approved :: Apache Software License
Requires-Python: >=3.8
Requires-Dist: Babel
Requires-Dist: clldutils>=3.18
Requires-Dist: legacy-cgi>=2.6; python_version >= "3.13"
Requires-Dist: pyramid>=1.10
Requires-Dist: pyramid_mako>=1.0
Requires-Dist: pyramid_tm
Requires-Dist: SQLAlchemy<2.0,>=1.4
Requires-Dist: zope.sqlalchemy
Requires-Dist: webassets>=0.12.1
Requires-Dist: markupsafe
Requires-Dist: rdflib>=4.1.1
Requires-Dist: nameparser
Provides-Extra: bootstrap
Requires-Dist: cookiecutter; extra == "bootstrap"
Requires-Dist: pycldf; extra == "bootstrap"
Provides-Extra: dev
Requires-Dist: cookiecutter; extra == "dev"
Requires-Dist: pycldf; extra == "dev"
Requires-Dist: cldfcatalog; extra == "dev"
Requires-Dist: waitress; extra == "dev"
Requires-Dist: pyramid_debugtoolbar; extra == "dev"
Requires-Dist: tox; extra == "dev"
Requires-Dist: flake8; extra == "dev"
Requires-Dist: wheel; extra == "dev"
Requires-Dist: twine; extra == "dev"
Requires-Dist: build; extra == "dev"
Provides-Extra: test
Requires-Dist: cookiecutter; extra == "test"
Requires-Dist: pytest>=6; extra == "test"
Requires-Dist: pytest-clld>=1.0.3; extra == "test"
Requires-Dist: pytest-mock; extra == "test"
Requires-Dist: pytest-cov; extra == "test"
Requires-Dist: coverage>=4.2; extra == "test"
Requires-Dist: zope.component>=3.11.0; extra == "test"
Provides-Extra: docs
Requires-Dist: Sphinx<7; extra == "docs"
Requires-Dist: docutils; extra == "docs"
Requires-Dist: repoze.sphinx.autointerface; extra == "docs"
